tinytapeout/promedio.v
module promedio#(parameter N=4)(
	input clk, reset, en,
	input [N-1:0] in,
	output reg [N-1:0] promedio
); 

reg [3:0] contador;

always @(posedge clk) begin
	if(reset) contador <= 0;
	else if(en) contador <= contador + 1;
end

always @(posedge clk) begin
	if(reset) promedio <= 0;
	else if(contador == 15) promedio <= promedio/15;
	else if(en) promedio <= promedio + in;
end	
	
endmodule

tinytapeout/contador.v
module contador(input osc_clk, input en, input reset, input clk, output reg [8:0] count);

reg aux;
reg pre_aux;

always @(posedge osc_clk) begin
	if(reset) aux <= 1;
	//else aux <= pre_aux;
end

always @(posedge osc_clk) begin
	if(clk && aux) begin
		aux <= 0;
		count <= 0;
	end
	else if(en) begin
		if(!clk) aux<= 1;
		count <= count + 1;
	end
end

endmodule

tinytapeout/NOR_2.v
`timescale 1ns / 1ps
//////////////////////////////////////////////////////////////////////////////////
// Company: 
// Engineer: 
// 
// Create Date: 22.03.2023 21:16:21
// Design Name: 
// Module Name: NOR_2
// Project Name: 
// Target Devices: 
// Tool Versions: 
// Description: 
// 
// Dependencies: 
// 
// Revision:
// Revision 0.01 - File Created
// Additional Comments:
// 
//////////////////////////////////////////////////////////////////////////////////


module NOR_2(output Y, input A, B);
nor #(2)(Y, A, B); 
endmodule

tinytapeout/test_ringosc_vargen.v
`timescale 1ns / 1ps
//////////////////////////////////////////////////////////////////////////////////
// Company: 
// Engineer: 
// 
// Create Date: 21.03.2023 20:42:16
// Design Name: 
// Module Name: test_ringosc_vargen
// Project Name: 
// Target Devices: 
// Tool Versions: 
// Description: 
// 
// Dependencies: 
// 
// Revision:
// Revision 0.01 - File Created
// Additional Comments:
// 
//////////////////////////////////////////////////////////////////////////////////


module test_ringosc_vargen(
    input en,
    output out
    );
   
    localparam etapas = 3;
    
    wire aux_wire [etapas:0];
    
    genvar i;
    generate
    for(i=0; i<etapas; i=i+1) begin
        NOR_2 inv(aux_wire[i+1], aux_wire[i], aux_wire[i]);
    end
    endgenerate
    
    assign aux_wire[0] = out & en;
    assign out = aux_wire[etapas];
    //assign in = out;
endmodule

tinytapeout/top_tinytapeout_v2.v
module top_tinytapeout_v2(input clk, input en, input reset, output wire [8:0] promedio);

wire out_osc;
wire [8:0] count;
test_ringosc_vargen osc(en, out_osc);
contador cont(out_osc, en, reset, clk, count);
promedio #(9) prom(clk, reset, en, count, promedio);

endmodule

tinytapeout/tb_v2.v
module tb_v2(

    );
    reg clk;
    reg en;
    reg reset;
    wire [8:0] promedio;
    top_tinytapeout_v2 DUT(clk, en, reset, promedio);
    
    always #500 clk = ~clk;
    
    initial begin
    $dumpfile("test.vcd");
    $dumpvars(0,tb_v2);
    reset = 1;
    clk=0;
    en = 0;
    #1000 en = 1;
    #1500 reset = 0;
    #20000 $finish;
    end
    
endmodule

tinytapeout/test.vcd
$date
	Wed Apr 12 14:55:33 2023
$end
$version
	Icarus Verilog
$end
$timescale
	1ps
$end
$scope module tb_v2 $end
$var wire 9 ! promedio [8:0] $end
$var reg 1 " clk $end
$var reg 1 # en $end
$var reg 1 $ reset $end
$scope module DUT $end
$var wire 1 " clk $end
$var wire 1 # en $end
$var wire 1 $ reset $end
$var wire 9 % promedio [8:0] $end
$var wire 1 & out_osc $end
$var wire 9 ' count [8:0] $end
$scope module cont $end
$var wire 1 " clk $end
$var wire 1 # en $end
$var wire 1 $ reset $end
$var wire 1 & osc_clk $end
$var reg 1 ( aux $end
$var reg 9 ) count [8:0] $end
$upscope $end
$scope module osc $end
$var wire 1 # en $end
$var wire 1 & out $end
$scope begin genblk1[0] $end
$scope module inv $end
$var wire 1 * A $end
$var wire 1 * B $end
$var wire 1 + Y $end
$upscope $end
$upscope $end
$scope begin genblk1[1] $end
$scope module inv $end
$var wire 1 + A $end
$var wire 1 + B $end
$var wire 1 , Y $end
$upscope $end
$upscope $end
$scope begin genblk1[2] $end
$scope module inv $end
$var wire 1 , A $end
$var wire 1 , B $end
$var wire 1 - Y $end
$upscope $end
$upscope $end
$upscope $end
$scope module prom $end
$var wire 1 " clk $end
$var wire 1 # en $end
$var wire 9 . in [8:0] $end
$var wire 1 $ reset $end
$var reg 4 / contador [3:0] $end
$var reg 9 0 promedio [8:0] $end
$upscope $end
$upscope $end
$upscope $end
$enddefinitions $end
#0
$dumpvars
bx 0
bx /
bx .
x-
x,
x+
0*
bx )
x(
bx '
x&
bx %
1$
0#
0"
bx !
$end
#2000
1+
#4000
0,
#6000
1(
1&
1-
#500000
b0 /
b0 !
b0 %
b0 0
1"
#1000000
1*
0"
1#
#1002000
0+
#1004000
1,
#1006000
0*
0&
0-
#1008000
1+
#1010000
0,
#1012000
1*
1&
1-
#1014000
0+
#1016000
1,
#1018000
0*
0&
0-
#1020000
1+
#1022000
0,
#1024000
1*
1&
1-
#1026000
0+
#1028000
1,
#1030000
0*
0&
0-
#1032000
1+
#1034000
0,
#1036000
1*
1&
1-
#1038000
0+
#1040000
1,
#1042000
0*
0&
0-
#1044000
1+
#1046000
0,
#1048000
1*
1&
1-
#1050000
0+
#1052000
1,
#1054000
0*
0&
0-
#1056000
1+
#1058000
0,
#1060000
1*
1&
1-
#1062000
0+
#1064000
1,
#1066000
0*
0&
0-
#1068000
1+
#1070000
0,
#1072000
1*
1&
1-
#1074000
0+
#1076000
1,
#1078000
0*
0&
0-
#1080000
1+
#1082000
0,
#1084000
1*
1&
1-
#1086000
0+
#1088000
1,
#1090000
0*
0&
0-
#1092000
1+
#1094000
0,
#1096000
1*
1&
1-
#1098000
0+
#1100000
1,
#1102000
0*
0&
0-
#1104000
1+
#1106000
0,
#1108000
1*
1&
1-
#1110000
0+
#1112000
1,
#1114000
0*
0&
0-
#1116000
1+
#1118000
0,
#1120000
1*
1&
1-
#1122000
0+
#1124000
1,
#1126000
0*
0&
0-
#1128000
1+
#1130000
0,
#1132000
1*
1&
1-
#1134000
0+
#1136000
1,
#1138000
0*
0&
0-
#1140000
1+
#1142000
0,
#1144000
1*
1&
1-
#1146000
0+
#1148000
1,
#1150000
0*
0&
0-
#1152000
1+
#1154000
0,
#1156000
1*
1&
1-
#1158000
0+
#1160000
1,
#1162000
0*
0&
0-
#1164000
1+
#1166000
0,
#1168000
1*
1&
1-
#1170000
0+
#1172000
1,
#1174000
0*
0&
0-
#1176000
1+
#1178000
0,
#1180000
1*
1&
1-
#1182000
0+
#1184000
1,
#1186000
0*
0&
0-
#1188000
1+
#1190000
0,
#1192000
1*
1&
1-
#1194000
0+
#1196000
1,
#1198000
0*
0&
0-
#1200000
1+
#1202000
0,
#1204000
1*
1&
1-
#1206000
0+
#1208000
1,
#1210000
0*
0&
0-
#1212000
1+
#1214000
0,
#1216000
1*
1&
1-
#1218000
0+
#1220000
1,
#1222000
0*
0&
0-
#1224000
1+
#1226000
0,
#1228000
1*
1&
1-
#1230000
0+
#1232000
1,
#1234000
0*
0&
0-
#1236000
1+
#1238000
0,
#1240000
1*
1&
1-
#1242000
0+
#1244000
1,
#1246000
0*
0&
0-
#1248000
1+
#1250000
0,
#1252000
1*
1&
1-
#1254000
0+
#1256000
1,
#1258000
0*
0&
0-
#1260000
1+
#1262000
0,
#1264000
1*
1&
1-
#1266000
0+
#1268000
1,
#1270000
0*
0&
0-
#1272000
1+
#1274000
0,
#1276000
1*
1&
1-
#1278000
0+
#1280000
1,
#1282000
0*
0&
0-
#1284000
1+
#1286000
0,
#1288000
1*
1&
1-
#1290000
0+
#1292000
1,
#1294000
0*
0&
0-
#1296000
1+
#1298000
0,
#1300000
1*
1&
1-
#1302000
0+
#1304000
1,
#1306000
0*
0&
0-
#1308000
1+
#1310000
0,
#1312000
1*
1&
1-
#1314000
0+
#1316000
1,
#1318000
0*
0&
0-
#1320000
1+
#1322000
0,
#1324000
1*
1&
1-
#1326000
0+
#1328000
1,
#1330000
0*
0&
0-
#1332000
1+
#1334000
0,
#1336000
1*
1&
1-
#1338000
0+
#1340000
1,
#1342000
0*
0&
0-
#1344000
1+
#1346000
0,
#1348000
1*
1&
1-
#1350000
0+
#1352000
1,
#1354000
0*
0&
0-
#1356000
1+
#1358000
0,
#1360000
1*
1&
1-
#1362000
0+
#1364000
1,
#1366000
0*
0&
0-
#1368000
1+
#1370000
0,
#1372000
1*
1&
1-
#1374000
0+
#1376000
1,
#1378000
0*
0&
0-
#1380000
1+
#1382000
0,
#1384000
1*
1&
1-
#1386000
0+
#1388000
1,
#1390000
0*
0&
0-
#1392000
1+
#1394000
0,
#1396000
1*
1&
1-
#1398000
0+
#1400000
1,
#1402000
0*
0&
0-
#1404000
1+
#1406000
0,
#1408000
1*
1&
1-
#1410000
0+
#1412000
1,
#1414000
0*
0&
0-
#1416000
1+
#1418000
0,
#1420000
1*
1&
1-
#1422000
0+
#1424000
1,
#1426000
0*
0&
0-
#1428000
1+
#1430000
0,
#1432000
1*
1&
1-
#1434000
0+
#1436000
1,
#1438000
0*
0&
0-
#1440000
1+
#1442000
0,
#1444000
1*
1&
1-
#1446000
0+
#1448000
1,
#1450000
0*
0&
0-
#1452000
1+
#1454000
0,
#1456000
1*
1&
1-
#1458000
0+
#1460000
1,
#1462000
0*
0&
0-
#1464000
1+
#1466000
0,
#1468000
1*
1&
1-
#1470000
0+
#1472000
1,
#1474000
0*
0&
0-
#1476000
1+
#1478000
0,
#1480000
1*
1&
1-
#1482000
0+
#1484000
1,
#1486000
0*
0&
0-
#1488000
1+
#1490000
0,
#1492000
1*
1&
1-
#1494000
0+
#1496000
1,
#1498000
0*
0&
0-
#1500000
1+
1"
#1502000
0,
#1504000
b0 '
b0 )
b0 .
1(
1*
1&
1-
#1506000
0+
#1508000
1,
#1510000
0*
0&
0-
#1512000
1+
#1514000
0,
#1516000
0(
1*
1&
1-
#1518000
0+
#1520000
1,
#1522000
0*
0&
0-
#1524000
1+
#1526000
0,
#1528000
1(
b1 '
b1 )
b1 .
1*
1&
1-
#1530000
0+
#1532000
1,
#1534000
0*
0&
0-
#1536000
1+
#1538000
0,
#1540000
b0 '
b0 )
b0 .
0(
1*
1&
1-
#1542000
0+
#1544000
1,
#1546000
0*
0&
0-
#1548000
1+
#1550000
0,
#1552000
1(
b1 '
b1 )
b1 .
1*
1&
1-
#1554000
0+
#1556000
1,
#1558000
0*
0&
0-
#1560000
1+
#1562000
0,
#1564000
b0 '
b0 )
b0 .
0(
1*
1&
1-
#1566000
0+
#1568000
1,
#1570000
0*
0&
0-
#1572000
1+
#1574000
0,
#1576000
1(
b1 '
b1 )
b1 .
1*
1&
1-
#1578000
0+
#1580000
1,
#1582000
0*
0&
0-
#1584000
1+
#1586000
0,
#1588000
b0 '
b0 )
b0 .
0(
1*
1&
1-
#1590000
0+
#1592000
1,
#1594000
0*
0&
0-
#1596000
1+
#1598000
0,
#1600000
1(
b1 '
b1 )
b1 .
1*
1&
1-
#1602000
0+
#1604000
1,
#1606000
0*
0&
0-
#1608000
1+
#1610000
0,
#1612000
b0 '
b0 )
b0 .
0(
1*
1&
1-
#1614000
0+
#1616000
1,
#1618000
0*
0&
0-
#1620000
1+
#1622000
0,
#1624000
1(
b1 '
b1 )
b1 .
1*
1&
1-
#1626000
0+
#1628000
1,
#1630000
0*
0&
0-
#1632000
1+
#1634000
0,
#1636000
b0 '
b0 )
b0 .
0(
1*
1&
1-
#1638000
0+
#1640000
1,
#1642000
0*
0&
0-
#1644000
1+
#1646000
0,
#1648000
1(
b1 '
b1 )
b1 .
1*
1&
1-
#1650000
0+
#1652000
1,
#1654000
0*
0&
0-
#1656000
1+
#1658000
0,
#1660000
b0 '
b0 )
b0 .
0(
1*
1&
1-
#1662000
0+
#1664000
1,
#1666000
0*
0&
0-
#1668000
1+
#1670000
0,
#1672000
1(
b1 '
b1 )
b1 .
1*
1&
1-
#1674000
0+
#1676000
1,
#1678000
0*
0&
0-
#1680000
1+
#1682000
0,
#1684000
b0 '
b0 )
b0 .
0(
1*
1&
1-
#1686000
0+
#1688000
1,
#1690000
0*
0&
0-
#1692000
1+
#1694000
0,
#1696000
1(
b1 '
b1 )
b1 .
1*
1&
1-
#1698000
0+
#1700000
1,
#1702000
0*
0&
0-
#1704000
1+
#1706000
0,
#1708000
b0 '
b0 )
b0 .
0(
1*
1&
1-
#1710000
0+
#1712000
1,
#1714000
0*
0&
0-
#1716000
1+
#1718000
0,
#1720000
1(
b1 '
b1 )
b1 .
1*
1&
1-
#1722000
0+
#1724000
1,
#1726000
0*
0&
0-
#1728000
1+
#1730000
0,
#1732000
b0 '
b0 )
b0 .
0(
1*
1&
1-
#1734000
0+
#1736000
1,
#1738000
0*
0&
0-
#1740000
1+
#1742000
0,
#1744000
1(
b1 '
b1 )
b1 .
1*
1&
1-
#1746000
0+
#1748000
1,
#1750000
0*
0&
0-
#1752000
1+
#1754000
0,
#1756000
b0 '
b0 )
b0 .
0(
1*
1&
1-
#1758000
0+
#1760000
1,
#1762000
0*
0&
0-
#1764000
1+
#1766000
0,
#1768000
1(
b1 '
b1 )
b1 .
1*
1&
1-
#1770000
0+
#1772000
1,
#1774000
0*
0&
0-
#1776000
1+
#1778000
0,
#1780000
b0 '
b0 )
b0 .
0(
1*
1&
1-
#1782000
0+
#1784000
1,
#1786000
0*
0&
0-
#1788000
1+
#1790000
0,
#1792000
1(
b1 '
b1 )
b1 .
1*
1&
1-
#1794000
0+
#1796000
1,
#1798000
0*
0&
0-
#1800000
1+
#1802000
0,
#1804000
b0 '
b0 )
b0 .
0(
1*
1&
1-
#1806000
0+
#1808000
1,
#1810000
0*
0&
0-
#1812000
1+
#1814000
0,
#1816000
1(
b1 '
b1 )
b1 .
1*
1&
1-
#1818000
0+
#1820000
1,
#1822000
0*
0&
0-
#1824000
1+
#1826000
0,
#1828000
b0 '
b0 )
b0 .
0(
1*
1&
1-
#1830000
0+
#1832000
1,
#1834000
0*
0&
0-
#1836000
1+
#1838000
0,
#1840000
1(
b1 '
b1 )
b1 .
1*
1&
1-
#1842000
0+
#1844000
1,
#1846000
0*
0&
0-
#1848000
1+
#1850000
0,
#1852000
b0 '
b0 )
b0 .
0(
1*
1&
1-
#1854000
0+
#1856000
1,
#1858000
0*
0&
0-
#1860000
1+
#1862000
0,
#1864000
1(
b1 '
b1 )
b1 .
1*
1&
1-
#1866000
0+
#1868000
1,
#1870000
0*
0&
0-
#1872000
1+
#1874000
0,
#1876000
b0 '
b0 )
b0 .
0(
1*
1&
1-
#1878000
0+
#1880000
1,
#1882000
0*
0&
0-
#1884000
1+
#1886000
0,
#1888000
1(
b1 '
b1 )
b1 .
1*
1&
1-
#1890000
0+
#1892000
1,
#1894000
0*
0&
0-
#1896000
1+
#1898000
0,
#1900000
b0 '
b0 )
b0 .
0(
1*
1&
1-
#1902000
0+
#1904000
1,
#1906000
0*
0&
0-
#1908000
1+
#1910000
0,
#1912000
1(
b1 '
b1 )
b1 .
1*
1&
1-
#1914000
0+
#1916000
1,
#1918000
0*
0&
0-
#1920000
1+
#1922000
0,
#1924000
b0 '
b0 )
b0 .
0(
1*
1&
1-
#1926000
0+
#1928000
1,
#1930000
0*
0&
0-
#1932000
1+
#1934000
0,
#1936000
1(
b1 '
b1 )
b1 .
1*
1&
1-
#1938000
0+
#1940000
1,
#1942000
0*
0&
0-
#1944000
1+
#1946000
0,
#1948000
b0 '
b0 )
b0 .
0(
1*
1&
1-
#1950000
0+
#1952000
1,
#1954000
0*
0&
0-
#1956000
1+
#1958000
0,
#1960000
1(
b1 '
b1 )
b1 .
1*
1&
1-
#1962000
0+
#1964000
1,
#1966000
0*
0&
0-
#1968000
1+
#1970000
0,
#1972000
b0 '
b0 )
b0 .
0(
1*
1&
1-
#1974000
0+
#1976000
1,
#1978000
0*
0&
0-
#1980000
1+
#1982000
0,
#1984000
1(
b1 '
b1 )
b1 .
1*
1&
1-
#1986000
0+
#1988000
1,
#1990000
0*
0&
0-
#1992000
1+
#1994000
0,
#1996000
b0 '
b0 )
b0 .
0(
1*
1&
1-
#1998000
0+
#2000000
1,
0"
#2002000
0*
0&
0-
#2004000
1+
#2006000
0,
#2008000
b1 '
b1 )
b1 .
1(
1*
1&
1-
#2010000
0+
#2012000
1,
#2014000
0*
0&
0-
#2016000
1+
#2018000
0,
#2020000
b10 '
b10 )
b10 .
1*
1&
1-
#2022000
0+
#2024000
1,
#2026000
0*
0&
0-
#2028000
1+
#2030000
0,
#2032000
b11 '
b11 )
b11 .
1*
1&
1-
#2034000
0+
#2036000
1,
#2038000
0*
0&
0-
#2040000
1+
#2042000
0,
#2044000
b100 '
b100 )
b100 .
1*
1&
1-
#2046000
0+
#2048000
1,
#2050000
0*
0&
0-
#2052000
1+
#2054000
0,
#2056000
b101 '
b101 )
b101 .
1*
1&
1-
#2058000
0+
#2060000
1,
#2062000
0*
0&
0-
#2064000
1+
#2066000
0,
#2068000
b110 '
b110 )
b110 .
1*
1&
1-
#2070000
0+
#2072000
1,
#2074000
0*
0&
0-
#2076000
1+
#2078000
0,
#2080000
b111 '
b111 )
b111 .
1*
1&
1-
#2082000
0+
#2084000
1,
#2086000
0*
0&
0-
#2088000
1+
#2090000
0,
#2092000
b1000 '
b1000 )
b1000 .
1*
1&
1-
#2094000
0+
#2096000
1,
#2098000
0*
0&
0-
#2100000
1+
#2102000
0,
#2104000
b1001 '
b1001 )
b1001 .
1*
1&
1-
#2106000
0+
#2108000
1,
#2110000
0*
0&
0-
#2112000
1+
#2114000
0,
#2116000
b1010 '
b1010 )
b1010 .
1*
1&
1-
#2118000
0+
#2120000
1,
#2122000
0*
0&
0-
#2124000
1+
#2126000
0,
#2128000
b1011 '
b1011 )
b1011 .
1*
1&
1-
#2130000
0+
#2132000
1,
#2134000
0*
0&
0-
#2136000
1+
#2138000
0,
#2140000
b1100 '
b1100 )
b1100 .
1*
1&
1-
#2142000
0+
#2144000
1,
#2146000
0*
0&
0-
#2148000
1+
#2150000
0,
#2152000
b1101 '
b1101 )
b1101 .
1*
1&
1-
#2154000
0+
#2156000
1,
#2158000
0*
0&
0-
#2160000
1+
#2162000
0,
#2164000
b1110 '
b1110 )
b1110 .
1*
1&
1-
#2166000
0+
#2168000
1,
#2170000
0*
0&
0-
#2172000
1+
#2174000
0,
#2176000
b1111 '
b1111 )
b1111 .
1*
1&
1-
#2178000
0+
#2180000
1,
#2182000
0*
0&
0-
#2184000
1+
#2186000
0,
#2188000
b10000 '
b10000 )
b10000 .
1*
1&
1-
#2190000
0+
#2192000
1,
#2194000
0*
0&
0-
#2196000
1+
#2198000
0,
#2200000
b10001 '
b10001 )
b10001 .
1*
1&
1-
#2202000
0+
#2204000
1,
#2206000
0*
0&
0-
#2208000
1+
#2210000
0,
#2212000
b10010 '
b10010 )
b10010 .
1*
1&
1-
#2214000
0+
#2216000
1,
#2218000
0*
0&
0-
#2220000
1+
#2222000
0,
#2224000
b10011 '
b10011 )
b10011 .
1*
1&
1-
#2226000
0+
#2228000
1,
#2230000
0*
0&
0-
#2232000
1+
#2234000
0,
#2236000
b10100 '
b10100 )
b10100 .
1*
1&
1-
#2238000
0+
#2240000
1,
#2242000
0*
0&
0-
#2244000
1+
#2246000
0,
#2248000
b10101 '
b10101 )
b10101 .
1*
1&
1-
#2250000
0+
#2252000
1,
#2254000
0*
0&
0-
#2256000
1+
#2258000
0,
#2260000
b10110 '
b10110 )
b10110 .
1*
1&
1-
#2262000
0+
#2264000
1,
#2266000
0*
0&
0-
#2268000
1+
#2270000
0,
#2272000
b10111 '
b10111 )
b10111 .
1*
1&
1-
#2274000
0+
#2276000
1,
#2278000
0*
0&
0-
#2280000
1+
#2282000
0,
#2284000
b11000 '
b11000 )
b11000 .
1*
1&
1-
#2286000
0+
#2288000
1,
#2290000
0*
0&
0-
#2292000
1+
#2294000
0,
#2296000
b11001 '
b11001 )
b11001 .
1*
1&
1-
#2298000
0+
#2300000
1,
#2302000
0*
0&
0-
#2304000
1+
#2306000
0,
#2308000
b11010 '
b11010 )
b11010 .
1*
1&
1-
#2310000
0+
#2312000
1,
#2314000
0*
0&
0-
#2316000
1+
#2318000
0,
#2320000
b11011 '
b11011 )
b11011 .
1*
1&
1-
#2322000
0+
#2324000
1,
#2326000
0*
0&
0-
#2328000
1+
#2330000
0,
#2332000
b11100 '
b11100 )
b11100 .
1*
1&
1-
#2334000
0+
#2336000
1,
#2338000
0*
0&
0-
#2340000
1+
#2342000
0,
#2344000
b11101 '
b11101 )
b11101 .
1*
1&
1-
#2346000
0+
#2348000
1,
#2350000
0*
0&
0-
#2352000
1+
#2354000
0,
#2356000
b11110 '
b11110 )
b11110 .
1*
1&
1-
#2358000
0+
#2360000
1,
#2362000
0*
0&
0-
#2364000
1+
#2366000
0,
#2368000
b11111 '
b11111 )
b11111 .
1*
1&
1-
#2370000
0+
#2372000
1,
#2374000
0*
0&
0-
#2376000
1+
#2378000
0,
#2380000
b100000 '
b100000 )
b100000 .
1*
1&
1-
#2382000
0+
#2384000
1,
#2386000
0*
0&
0-
#2388000
1+
#2390000
0,
#2392000
b100001 '
b100001 )
b100001 .
1*
1&
1-
#2394000
0+
#2396000
1,
#2398000
0*
0&
0-
#2400000
1+
#2402000
0,
#2404000
b100010 '
b100010 )
b100010 .
1*
1&
1-
#2406000
0+
#2408000
1,
#2410000
0*
0&
0-
#2412000
1+
#2414000
0,
#2416000
b100011 '
b100011 )
b100011 .
1*
1&
1-
#2418000
0+
#2420000
1,
#2422000
0*
0&
0-
#2424000
1+
#2426000
0,
#2428000
b100100 '
b100100 )
b100100 .
1*
1&
1-
#2430000
0+
#2432000
1,
#2434000
0*
0&
0-
#2436000
1+
#2438000
0,
#2440000
b100101 '
b100101 )
b100101 .
1*
1&
1-
#2442000
0+
#2444000
1,
#2446000
0*
0&
0-
#2448000
1+
#2450000
0,
#2452000
b100110 '
b100110 )
b100110 .
1*
1&
1-
#2454000
0+
#2456000
1,
#2458000
0*
0&
0-
#2460000
1+
#2462000
0,
#2464000
b100111 '
b100111 )
b100111 .
1*
1&
1-
#2466000
0+
#2468000
1,
#2470000
0*
0&
0-
#2472000
1+
#2474000
0,
#2476000
b101000 '
b101000 )
b101000 .
1*
1&
1-
#2478000
0+
#2480000
1,
#2482000
0*
0&
0-
#2484000
1+
#2486000
0,
#2488000
b101001 '
b101001 )
b101001 .
1*
1&
1-
#2490000
0+
#2492000
1,
#2494000
0*
0&
0-
#2496000
1+
#2498000
0,
#2500000
b0 '
b0 )
b0 .
0(
b1 /
b101001 !
b101001 %
b101001 0
1*
1&
1-
1"
0$
#2502000
0+
#2504000
1,
#2506000
0*
0&
0-
#2508000
1+
#2510000
0,
#2512000
b1 '
b1 )
b1 .
1*
1&
1-
#2514000
0+
#2516000
1,
#2518000
0*
0&
0-
#2520000
1+
#2522000
0,
#2524000
b10 '
b10 )
b10 .
1*
1&
1-
#2526000
0+
#2528000
1,
#2530000
0*
0&
0-
#2532000
1+
#2534000
0,
#2536000
b11 '
b11 )
b11 .
1*
1&
1-
#2538000
0+
#2540000
1,
#2542000
0*
0&
0-
#2544000
1+
#2546000
0,
#2548000
b100 '
b100 )
b100 .
1*
1&
1-
#2550000
0+
#2552000
1,
#2554000
0*
0&
0-
#2556000
1+
#2558000
0,
#2560000
b101 '
b101 )
b101 .
1*
1&
1-
#2562000
0+
#2564000
1,
#2566000
0*
0&
0-
#2568000
1+
#2570000
0,
#2572000
b110 '
b110 )
b110 .
1*
1&
1-
#2574000
0+
#2576000
1,
#2578000
0*
0&
0-
#2580000
1+
#2582000
0,
#2584000
b111 '
b111 )
b111 .
1*
1&
1-
#2586000
0+
#2588000
1,
#2590000
0*
0&
0-
#2592000
1+
#2594000
0,
#2596000
b1000 '
b1000 )
b1000 .
1*
1&
1-
#2598000
0+
#2600000
1,
#2602000
0*
0&
0-
#2604000
1+
#2606000
0,
#2608000
b1001 '
b1001 )
b1001 .
1*
1&
1-
#2610000
0+
#2612000
1,
#2614000
0*
0&
0-
#2616000
1+
#2618000
0,
#2620000
b1010 '
b1010 )
b1010 .
1*
1&
1-
#2622000
0+
#2624000
1,
#2626000
0*
0&
0-
#2628000
1+
#2630000
0,
#2632000
b1011 '
b1011 )
b1011 .
1*
1&
1-
#2634000
0+
#2636000
1,
#2638000
0*
0&
0-
#2640000
1+
#2642000
0,
#2644000
b1100 '
b1100 )
b1100 .
1*
1&
1-
#2646000
0+
#2648000
1,
#2650000
0*
0&
0-
#2652000
1+
#2654000
0,
#2656000
b1101 '
b1101 )
b1101 .
1*
1&
1-
#2658000
0+
#2660000
1,
#2662000
0*
0&
0-
#2664000
1+
#2666000
0,
#2668000
b1110 '
b1110 )
b1110 .
1*
1&
1-
#2670000
0+
#2672000
1,
#2674000
0*
0&
0-
#2676000
1+
#2678000
0,
#2680000
b1111 '
b1111 )
b1111 .
1*
1&
1-
#2682000
0+
#2684000
1,
#2686000
0*
0&
0-
#2688000
1+
#2690000
0,
#2692000
b10000 '
b10000 )
b10000 .
1*
1&
1-
#2694000
0+
#2696000
1,
#2698000
0*
0&
0-
#2700000
1+
#2702000
0,
#2704000
b10001 '
b10001 )
b10001 .
1*
1&
1-
#2706000
0+
#2708000
1,
#2710000
0*
0&
0-
#2712000
1+
#2714000
0,
#2716000
b10010 '
b10010 )
b10010 .
1*
1&
1-
#2718000
0+
#2720000
1,
#2722000
0*
0&
0-
#2724000
1+
#2726000
0,
#2728000
b10011 '
b10011 )
b10011 .
1*
1&
1-
#2730000
0+
#2732000
1,
#2734000
0*
0&
0-
#2736000
1+
#2738000
0,
#2740000
b10100 '
b10100 )
b10100 .
1*
1&
1-
#2742000
0+
#2744000
1,
#2746000
0*
0&
0-
#2748000
1+
#2750000
0,
#2752000
b10101 '
b10101 )
b10101 .
1*
1&
1-
#2754000
0+
#2756000
1,
#2758000
0*
0&
0-
#2760000
1+
#2762000
0,
#2764000
b10110 '
b10110 )
b10110 .
1*
1&
1-
#2766000
0+
#2768000
1,
#2770000
0*
0&
0-
#2772000
1+
#2774000
0,
#2776000
b10111 '
b10111 )
b10111 .
1*
1&
1-
#2778000
0+
#2780000
1,
#2782000
0*
0&
0-
#2784000
1+
#2786000
0,
#2788000
b11000 '
b11000 )
b11000 .
1*
1&
1-
#2790000
0+
#2792000
1,
#2794000
0*
0&
0-
#2796000
1+
#2798000
0,
#2800000
b11001 '
b11001 )
b11001 .
1*
1&
1-
#2802000
0+
#2804000
1,
#2806000
0*
0&
0-
#2808000
1+
#2810000
0,
#2812000
b11010 '
b11010 )
b11010 .
1*
1&
1-
#2814000
0+
#2816000
1,
#2818000
0*
0&
0-
#2820000
1+
#2822000
0,
#2824000
b11011 '
b11011 )
b11011 .
1*
1&
1-
#2826000
0+
#2828000
1,
#2830000
0*
0&
0-
#2832000
1+
#2834000
0,
#2836000
b11100 '
b11100 )
b11100 .
1*
1&
1-
#2838000
0+
#2840000
1,
#2842000
0*
0&
0-
#2844000
1+
#2846000
0,
#2848000
b11101 '
b11101 )
b11101 .
1*
1&
1-
#2850000
0+
#2852000
1,
#2854000
0*
0&
0-
#2856000
1+
#2858000
0,
#2860000
b11110 '
b11110 )
b11110 .
1*
1&
1-
#2862000
0+
#2864000
1,
#2866000
0*
0&
0-
#2868000
1+
#2870000
0,
#2872000
b11111 '
b11111 )
b11111 .
1*
1&
1-
#2874000
0+
#2876000
1,
#2878000
0*
0&
0-
#2880000
1+
#2882000
0,
#2884000
b100000 '
b100000 )
b100000 .
1*
1&
1-
#2886000
0+
#2888000
1,
#2890000
0*
0&
0-
#2892000
1+
#2894000
0,
#2896000
b100001 '
b100001 )
b100001 .
1*
1&
1-
#2898000
0+
#2900000
1,
#2902000
0*
0&
0-
#2904000
1+
#2906000
0,
#2908000
b100010 '
b100010 )
b100010 .
1*
1&
1-
#2910000
0+
#2912000
1,
#2914000
0*
0&
0-
#2916000
1+
#2918000
0,
#2920000
b100011 '
b100011 )
b100011 .
1*
1&
1-
#2922000
0+
#2924000
1,
#2926000
0*
0&
0-
#2928000
1+
#2930000
0,
#2932000
b100100 '
b100100 )
b100100 .
1*
1&
1-
#2934000
0+
#2936000
1,
#2938000
0*
0&
0-
#2940000
1+
#2942000
0,
#2944000
b100101 '
b100101 )
b100101 .
1*
1&
1-
#2946000
0+
#2948000
1,
#2950000
0*
0&
0-
#2952000
1+
#2954000
0,
#2956000
b100110 '
b100110 )
b100110 .
1*
1&
1-
#2958000
0+
#2960000
1,
#2962000
0*
0&
0-
#2964000
1+
#2966000
0,
#2968000
b100111 '
b100111 )
b100111 .
1*
1&
1-
#2970000
0+
#2972000
1,
#2974000
0*
0&
0-
#2976000
1+
#2978000
0,
#2980000
b101000 '
b101000 )
b101000 .
1*
1&
1-
#2982000
0+
#2984000
1,
#2986000
0*
0&
0-
#2988000
1+
#2990000
0,
#2992000
b101001 '
b101001 )
b101001 .
1*
1&
1-
#2994000
0+
#2996000
1,
#2998000
0*
0&
0-
#3000000
1+
0"
#3002000
0,
#3004000
b101010 '
b101010 )
b101010 .
1(
1*
1&
1-
#3006000
0+
#3008000
1,
#3010000
0*
0&
0-
#3012000
1+
#3014000
0,
#3016000
b101011 '
b101011 )
b101011 .
1*
1&
1-
#3018000
0+
#3020000
1,
#3022000
0*
0&
0-
#3024000
1+
#3026000
0,
#3028000
b101100 '
b101100 )
b101100 .
1*
1&
1-
#3030000
0+
#3032000
1,
#3034000
0*
0&
0-
#3036000
1+
#3038000
0,
#3040000
b101101 '
b101101 )
b101101 .
1*
1&
1-
#3042000
0+
#3044000
1,
#3046000
0*
0&
0-
#3048000
1+
#3050000
0,
#3052000
b101110 '
b101110 )
b101110 .
1*
1&
1-
#3054000
0+
#3056000
1,
#3058000
0*
0&
0-
#3060000
1+
#3062000
0,
#3064000
b101111 '
b101111 )
b101111 .
1*
1&
1-
#3066000
0+
#3068000
1,
#3070000
0*
0&
0-
#3072000
1+
